Metadata-Version: 1.0
Name: Paulosdistributions
Version: 0.1
Summary: Gaussian distributions
Home-page: UNKNOWN
Author: osinowo paul
Author-email: osinowo62@gmail.com
License: UNKNOWN
Platform: UNKNOWN
